aioweenect/__init__.py
aioweenect/aioweenect.py
aioweenect/exceptions.py
aioweenect/zone_modes.py
aioweenect-1.1.5.dist-info/METADATA
aioweenect-1.1.5.dist-info/WHEEL
aioweenect-1.1.5.dist-info/licenses/LICENSE
aioweenect-1.1.5.dist-info/RECORD
