Metadata-Version: 2.3
Name: aioweenect
Version: 1.1.5
Summary: Asynchronous Python client for the weenect API
Author-email: Kevin Stillhammer <kevin.stillhammer@gmail.com>
License-Expression: MIT
License-File: LICENSE
Classifier: License :: OSI Approved :: MIT License
Requires-Python: >=3.9
Requires-Dist: aiohttp>=3.10.1
